yee/__init__.py
yee/cli.py
yee/yee.py
yee_cli-0.1.2.dist-info/entry_points.txt
yee_cli-0.1.2.dist-info/LICENSE
yee_cli-0.1.2.dist-info/WHEEL
yee_cli-0.1.2.dist-info/METADATA
yee_cli-0.1.2.dist-info/RECORD
