Metadata-Version: 2.1
Name: yee-cli
Version: 0.1.2
Summary: Simple Yeelight Room control CLI written in Python.
Home-page: https://github.com/adamwojt/yee-cli
License: MIT
Keywords: yee-cli
Author: Adam Wojtczak
Author-email: adam1edinburgh@gmail.com
Requires-Python: >=3.6,<4.0
Classifier: Development Status :: 2 - Pre-Alpha
Classifier: Intended Audience :: Developers
Classifier: License :: OSI Approved :: MIT License
Classifier: Natural Language :: English
Classifier: Programming Language :: Python
Classifier: Programming Language :: Python :: 3
Classifier: Programming Language :: Python :: 3.6
Classifier: Programming Language :: Python :: 3.7
Classifier: Programming Language :: Python :: 3.8
Classifier: Programming Language :: Python :: 3.9
Classifier: Programming Language :: Python :: Implementation :: CPython
Classifier: Programming Language :: Python :: Implementation :: PyPy
Classifier: Topic :: Software Development
Requires-Dist: Click (>=7.0,<8.0)
Requires-Dist: webcolors (>=1.11.1,<2.0.0)
Requires-Dist: yeelight (>=0.5.4,<0.6.0)
Project-URL: Bug Tracker, https://github.com/adamwojt/yee-cli/issues
Project-URL: Documentation, https://github.com/adamwojt/yee-cli
Project-URL: Repository, https://github.com/adamwojt/yee-cli
Project-URL: Source, https://github.com/adamwojt/yee-cli
